[{"nume": "Alba", "latitudine": 46.067341, "longitudine": 23.580870},
  {"nume": "Arad", "latitudine": 46.175968, "longitudine": 21.319000},
  {"nume": "Argeş", "latitudine": 44.858501, "longitudine": 24.870630},
  {"nume": "Bacău", "latitudine": 46.562031, "longitudine": 26.912060},
  {"nume": "Bihor", "latitudine": 47.055500, "longitudine": 21.928030},
  {"nume": "Bistriţa-Năsăud", "latitudine": 47.132210, "longitudine": 24.495119},
  {"nume": "Botoşani", "latitudine": 47.744999, "longitudine": 26.662130},
  {"nume": "Brăila", "latitudine": 45.270962, "longitudine": 27.974331},
  {"nume": "Braşov", "latitudine": 45.649490, "longitudine": 25.606550},
  {"nume": "Bucureşti", "latitudine": 44.435580, "longitudine": 26.102220},
  {"nume": "Buzău", "latitudine": 45.153591, "longitudine": 26.820169},
  {"nume": "Călăraşi", "latitudine": 44.191368, "longitudine": 27.332649},
  {"nume": "Caraş-Severin", "latitudine": 45.288269, "longitudine": 21.885590},
  {"nume": "Cluj", "latitudine": 46.770920, "longitudine": 23.589920},
  {"nume": "Constanţa", "latitudine": 44.177270, "longitudine": 28.652880},
  {"nume": "Covasna", "latitudine": 46.002369, "longitudine": 26.137730},
  {"nume": "Dâmboviţa", "latitudine": 44.926899, "longitudine": 25.457319},
  {"nume": "Dolj", "latitudine": 44.318378, "longitudine": 23.796400},
  {"nume": "Galaţi", "latitudine": 45.438220, "longitudine": 28.056340},
  {"nume": "Giurgiu", "latitudine": 43.895390, "longitudine": 25.967060},
  {"nume": "Gorj", "latitudine": 45.042309, "longitudine": 23.270969},
  {"nume": "Harghita", "latitudine": 46.359830, "longitudine": 25.802560},
  {"nume": "Hunedoara", "latitudine": 45.752361, "longitudine": 22.896049},
  {"nume": "Ialomiţa", "latitudine": 44.627110, "longitudine": 27.254560},
  {"nume": "Iaşi", "latitudine": 47.159810, "longitudine": 27.587200},
  {"nume": "Ilfov", "latitudine": 44.309448, "longitudine": 26.017920},
  {"nume": "Maramureş", "latitudine": 47.671160, "longitudine": 23.980080},
  {"nume": "Mehedinţi", "latitudine": 44.586800, "longitudine": 22.784110},
  {"nume": "Mureş", "latitudine": 46.542680, "longitudine": 24.557870},
  {"nume": "Neamţ", "latitudine": 46.931810, "longitudine": 26.369690},
  {"nume": "Olt", "latitudine": 44.364320, "longitudine": 24.265940},
  {"nume": "Prahova", "latitudine": 45.114319, "longitudine": 26.014240},
  {"nume": "Sălaj", "latitudine": 47.184120, "longitudine": 23.105040},
  {"nume": "Satu Mare", "latitudine": 47.793301, "longitudine": 22.877081},
  {"nume": "Sibiu", "latitudine": 45.796928, "longitudine": 24.149990},
  {"nume": "Suceava", "latitudine": 47.640942, "longitudine": 26.246441},
  {"nume": "Teleorman", "latitudine": 44.029840, "longitudine": 25.197100},
  {"nume": "Timiş", "latitudine": 45.750969, "longitudine": 21.226200},
  {"nume": "Tulcea", "latitudine": 45.176731, "longitudine": 28.805229},
  {"nume": "Vâlcea", "latitudine": 45.106579, "longitudine": 24.365210},
  {"nume": "Vaslui", "latitudine": 46.638088, "longitudine": 27.728760},
  {"nume": "Vrancea", "latitudine": 45.787609, "longitudine": 26.978649}]


